[
  {
    "resource_state": 2,
    "athlete": {
      "id": 26046377,
      "resource_state": 1
    },
    "name": "Morning Run",
    "distance": 11643.0,
    "moving_time": 3910,
    "elapsed_time": 4245,
    "total_elevation_gain": 40.0,
    "type": "Run",
    "sport_type": "Run",
    "workout_type": null,
    "device_name": "COROS PACE 3",
    "id": 16319990768,
    "start_date": "2025-11-01T10:08:19Z",
    "start_date_local": "2025-11-01T05:08:19Z",
    "timezone": "(GMT-06:00) America/Chicago",
    "utc_offset": -18000.0,
    "location_city": null,
    "location_state": null,
    "location_country": null,
    "achievement_count": 0,
    "kudos_count": 3,
    "comment_count": 0,
    "athlete_count": 1,
    "photo_count": 0,
    "map": {
      "id": "a16319990768",
      "summary_polyline": "uujiEj_amQi@Gs@AiBBcBAiA@G@IDIRGdBG\\IFWDaAAWCIEEGCKAoDAWCIGIUCwBDGBEFAJ?jLCZKNGBk@Fm@Re@Dw@L}Ab@yBd@{AVcCr@mAX{@N{@Xa@^IRCV@xCAHEDuHBkAB]?i@E{@@g@FeA?_AFeALeBd@iAl@iA~@EFATFVXj@FR@^C\\EXQr@Ml@E`AMz@ETQ\\IVWdA[lBM~@IlAEbC`@tHJ`ABz@Db@Jn@L`@^v@f@v@HZ?JMTm@n@y@l@KP?HXd@Pj@PrABpAIlKKjBSrA_@|AQtBKl@A\\BfAC`GIvACHKRQJI@sEAkC@u@BaBCkA@aBJiB?IBMPC`@B`BGdAAvICn@BfACbGEt@@vCG`B?lDJbBAzA@JBFRFjAER@FBFTDpAGhC?~DG`@Uj@BVR\\ZP^Dv@CJ@RRx@jAZHd@Eb@IVAzBV~@?pAE`@H\\RHCDI@OEy@Dg@@[Ig@EoAFWPM`@GdAHl@GT?`@JRN`@`@^JVAv@Ix@@TC^OJAJ?RJNTBJ@fABXFXTl@FVD^Dz@TbBC~A@t@KnALzAGnADxAKzA@t@H~@KlA@XHRF@^K\\?r@Jr@?THRLTFdB@j@C^FX@~BEzHAz@CdA@xAJhAA`AExADt@A`@@HAFEHWBYCaBBkEGqDD_MGyDBaD@_ICaBBoABsMA{B?iEDu@\\gB\\{@d@q@Jc@@MKs@Gu@C}AEmF@}ARiAAKY_AaAaGIcC?wBI_@HWBK?y@Di@@qAAk@Iu@DcA@kC@eA?eNDqGAkB@uDB_DCi@@kGBwDAyEDeF?SEQCwABg@@mDAwAFoBAs@EAaARSHAF@DHBp@@lAS\\OPQFIFWN}@P_@T[ZWVMZI|@K\\u@BWAyADWFETC|ADnF?",
      "resource_state": 2
    },
    "trainer": false,
    "commute": false,
    "manual": false,
    "private": false,
    "visibility": "everyone",
    "flagged": false,
    "gear_id": "g26559367",
    "start_latlng": [33.16, -96.68],
    "end_latlng": [33.16, -96.68],
    "average_speed": 2.978,
    "max_speed": 4.5,
    "average_cadence": 84.8,
    "average_watts": 212.1,
    "max_watts": 261,
    "weighted_average_watts": 207,
    "device_watts": true,
    "kilojoules": 829.4,
    "has_heartrate": true,
    "average_heartrate": 126.4,
    "max_heartrate": 160.0,
    "heartrate_opt_out": false,
    "display_hide_heartrate_option": true,
    "elev_high": 235.0,
    "elev_low": 201.0,
    "upload_id": 17405063286,
    "upload_id_str": "17405063286",
    "external_id": "472982226898812929.fit",
    "from_accepted_tag": false,
    "pr_count": 0,
    "total_photo_count": 0,
    "has_kudoed": false,
    "suffer_score": 18.0
  }
]
